{
  "minecraft:recipes/misc/charcoal": {
    "criteria": {
      "has_log": "2020-01-15 22:17:35 +0100"
    },
    "done": true
  },
  "minecraft:recipes/decorations/campfire": {
    "criteria": {
      "has_coal": "2020-01-15 22:37:56 +0100"
    },
    "done": true
  },
  "minecraft:recipes/building_blocks/jungle_wood": {
    "criteria": {
      "has_log": "2020-01-15 22:17:35 +0100"
    },
    "done": true
  },
  "minecraft:recipes/building_blocks/jack_o_lantern": {
    "criteria": {
      "has_carved_pumpkin": "2020-01-15 22:28:28 +0100"
    },
    "done": true
  },
  "minecraft:recipes/food/pumpkin_pie": {
    "criteria": {
      "has_carved_pumpkin": "2020-01-15 22:28:28 +0100"
    },
    "done": true
  },
  "minecraft:recipes/building_blocks/jungle_planks": {
    "criteria": {
      "has_log": "2020-01-15 22:17:35 +0100"
    },
    "done": true
  },
  "minecraft:recipes/building_blocks/coal_block": {
    "criteria": {
      "has_coal": "2020-01-15 22:37:56 +0100"
    },
    "done": true
  },
  "minecraft:adventure/adventuring_time": {
    "criteria": {
      "minecraft:plains": "2020-01-15 22:14:52 +0100"
    },
    "done": false
  },
  "DataVersion": 2227
}